deephalo/__init__.py
deephalo/config.toml
deephalo/halo_cli.py
deephalo/main.py
deephalo/parameters.py
deephalo/assets/pretrained_models/anomaly_detection_model.h5
deephalo/assets/pretrained_models/isonn_element_prediction_model.h5
deephalo/dataset/__init__.py
deephalo/dataset/data_creation.py
deephalo/dataset/fake_isotope_generator.py
deephalo/dataset/training_dataset_generator.py
deephalo/dereplication/__init__.py
deephalo/dereplication/database_processing.py
deephalo/dereplication/dereplication2networks.py
deephalo/dereplication/dereplication_ms1.py
deephalo/model/ROC_curve.py
deephalo/model/__init__.py
deephalo/model/anomaly_detector_model.py
deephalo/model/model_build.py
deephalo/model/model_evaluation.py
deephalo/model/model_training.py
deephalo/model/training_data.py
deephalo/msanalysis/__init__.py
deephalo/msanalysis/halogen_scorer.py
deephalo/msanalysis/isotope_extraction.py
deephalo/msanalysis/ms_analyzer.py
deephalo-1.0.0.dist-info/licenses/LICENSE
deephalo-1.0.0.dist-info/METADATA
deephalo-1.0.0.dist-info/WHEEL
deephalo-1.0.0.dist-info/entry_points.txt
deephalo-1.0.0.dist-info/top_level.txt
deephalo-1.0.0.dist-info/RECORD
